<?xml version="1.0" encoding="UTF-8"?>
<teiCorpus xmlns="http://www.tei-c.org/ns/1.0" xmlns:xi="http://www.w3.org/2001/XInclude">
  <teiHeader>
    <fileDesc>
      <titleStmt>
        <title>Swedish Drama Corpus</title>
      </titleStmt>
      <publicationStmt>
        <publisher>DraCor</publisher>
        <idno type="URI" xml:base="https://dracor.org/">swe</idno>
        <idno type="repo">https://github.com/dracor-org/swedracor</idno>
        <availability>
          <license target="https://creativecommons.org/licenses/by-sa/3.0/">
            CC BY-SA 3.0
          </license>
        </availability>
      </publicationStmt>
    </fileDesc>
    <encodingDesc>
      <projectDesc>
        <p>
          Derived from the
          <ref target="http://www.dramawebben.se/sida/edrama">eDrama</ref>
          project. Features 68 Swedish plays from around 1880 to 1900. More
          information in the
          <ref target="https://github.com/dracor-org/swedracor">README on
          GitHub</ref>.
        </p>
      </projectDesc>
    </encodingDesc>
  </teiHeader>
</teiCorpus>
